## HB AGE CALCULATOR.md
CHANGELOG.txt
MANIFEST.in
README.md
setup.py
hbagecalculator/__init__.py
hbagecalculator.egg-info/PKG-INFO
hbagecalculator.egg-info/SOURCES.txt
hbagecalculator.egg-info/dependency_links.txt
hbagecalculator.egg-info/requires.txt
hbagecalculator.egg-info/top_level.txt